dectest/__init__.py
dectest/_decorators.py
dectest/_testcase.py
dectest/_types.py
dectest/py.typed
dectest-1.1.1.dist-info/LICENSE
dectest-1.1.1.dist-info/METADATA
dectest-1.1.1.dist-info/WHEEL
dectest-1.1.1.dist-info/top_level.txt
dectest-1.1.1.dist-info/RECORD
