Metadata-Version: 2.1
Name: dectest
Version: 1.1.1
Summary: Improved TestCase class
Home-page: https://github.com/srittau/python-dectest
Author: Sebastian Rittau
Author-email: srittau@rittau.biz
License: MIT
Platform: UNKNOWN
Classifier: Development Status :: 5 - Production/Stable
Classifier: Intended Audience :: Developers
Classifier: License :: OSI Approved :: MIT License
Classifier: Programming Language :: Python :: 3
Classifier: Programming Language :: Python :: 3.5
Classifier: Programming Language :: Python :: 3.6
Classifier: Programming Language :: Python :: 3.7
Classifier: Topic :: Software Development :: Quality Assurance
Classifier: Topic :: Software Development :: Testing
Requires-Python: >=3.5
